pegasus_installer/__init__.py
pegasus_installer/__main__.py
pegasus_installer-0.1.0.dist-info/LICENSE
pegasus_installer-0.1.0.dist-info/METADATA
pegasus_installer-0.1.0.dist-info/WHEEL
pegasus_installer-0.1.0.dist-info/entry_points.txt
pegasus_installer-0.1.0.dist-info/top_level.txt
pegasus_installer-0.1.0.dist-info/RECORD
