Metadata-Version: 2.1
Name: pegasus-installer
Version: 0.1.0
Summary: Pegasus Installer Package
Home-page: https://www.saaspegasus.com/
Author: Cory Zue
Author-email: cory@saaspegasus.com
License: UNKNOWN
Platform: UNKNOWN
Classifier: Programming Language :: Python :: 3
Classifier: License :: OSI Approved :: MIT License
Classifier: Operating System :: OS Independent
Requires-Python: >=3.7
Requires-Dist: cookiecutter (>=1.7.2)
Requires-Dist: PyYAML (>=5.3.1)
